{
  "stac_version": "1.0.0",
  "type": "Feature",
  "id": "prototype_20240618",
  "stac_extensions": [
    "https://stac-extensions.github.io/eo/v1.1.0/schema.json",
    "https://stac-extensions.github.io/projection/v1.1.0/schema.json",
    "https://stac-extensions.github.io/raster/v1.1.0/schema.json",
    "https://stac-extensions.github.io/view/v1.0.0/schema.json"
  ],
  "bbox": [5.7, 52.24, 5.78, 52.28],
  "geometry": {
    "type": "Polygon",
    "coordinates": [
      [
        [5.7, 52.24],
        [5.78, 52.24],
        [5.78, 52.28],
        [5.7, 52.28],
        [5.7, 52.24]
      ]
    ]
  },
  "properties": {
    "datetime": "2024-06-18 10:42:00",
    "eo:cloud_cover": 5,
    "hydra:site_id": "NL-Loo",
    "hydra:crop": "potato",
    "hydra:plot_id": "P23",
    "hydra:treatment": "infected",
    "hydra:disease_name": "Flavesce doree",
    "hydra:disease_stage": "early",
    "hydra:incidence_pct": 12.5,
    "hydra:severity_score": 1,
    "hydra:severity_scale": "0-5_visual",
    "hydra:assessment_method": "visual",
    "hydra:label_source": "field",
    "hydra:label_confidence": 0.85,
    "hydra:air_temperature_c": 22.1,
    "hydra:relative_humidity_pct": 58,
    "hydra:wind_speed_ms": 3.2,
    "hydra:precip_24h_mm": 0,
    "hydra:vpd_kpa": 1.4,
    "hydra:has_field_data": true,
    "hydra:field_protocol": "HYDRA-EO_field_v1",
    "hydra:field_measurements": ["LAI", "Chl", "visual_disease_score", "leaf_temperature"],
    "hydra:field_qc_status": "qc1",
    "hydra:field_dataset_id": "hydraeo-field-nlloo-2024-v01"
  },
  "assets": {
    "reflectance": {
      "href": "https://storage.example.org/hydraeo/prototype/20240618/reflectance_cog.tif",
      "type": "image/tiff; application=geotiff; profile=cloud-optimized",
      "roles": "data"
    },
    "sif": {
      "href": "https://storage.example.org/hydraeo/prototype/20240618/sif_cog.tif",
      "type": "image/tiff; application=geotiff; profile=cloud-optimized",
      "roles": "data"
    },
    "mask": {
      "href": "https://storage.example.org/hydraeo/prototype/20240618/mask_cog.tif",
      "type": "image/tiff; application=geotiff; profile=cloud-optimized",
      "roles": "metadata"
    },
    "field_table": {
      "href": "https://storage.example.org/hydraeo/prototype/20240618/field_table.csv",
      "type": "text/csv",
      "roles": "metadata"
    },
    "field_protocol": {
      "href": "https://storage.example.org/hydraeo/prototype/protocols/HYDRA-EO_field_v1.pdf",
      "type": "application/pdf",
      "roles": "metadata"
    }
  },
  "links": [
    {
      "rel": "self",
      "href": "./prototype_20240618.json",
      "type": "application/json"
    },
    {
      "rel": "collection",
      "href": "../../collections/hydraeo_prototype/collection.json",
      "type": "application/json"
    },
    {
      "rel": "parent",
      "href": "../../collections/hydraeo_prototype/collection.json",
      "type": "application/json"
    },
    {
      "rel": "root",
      "href": "../../catalog.json",
      "type": "application/json"
    }
  ]
}
